pymongo_admin/__init__.py
pymongo_admin/mongo_admin.py
admongo-0.1.0.dist-info/LICENSE
admongo-0.1.0.dist-info/METADATA
admongo-0.1.0.dist-info/WHEEL
admongo-0.1.0.dist-info/entry_points.txt
admongo-0.1.0.dist-info/top_level.txt
admongo-0.1.0.dist-info/RECORD
